teradatasqlalchemy/__init__.py
teradatasqlalchemy/base.py
teradatasqlalchemy/compiler.py
teradatasqlalchemy/dialect.py
teradatasqlalchemy/options.py
teradatasqlalchemy/requirements.py
teradatasqlalchemy/resolver.py
teradatasqlalchemy/restricted_words.py
teradatasqlalchemy/types.py
teradatasqlalchemy/utils.py
teradatasqlalchemy/vernumber.py
teradatasqlalchemy/telemetry/__init__.py
teradatasqlalchemy/telemetry/queryband.py
teradatasqlalchemy-20.0.0.9.data/data/teradatasqlalchemy/LICENSE-3RD-PARTY.pdf
teradatasqlalchemy-20.0.0.9.data/data/teradatasqlalchemy/LICENSE.pdf
teradatasqlalchemy-20.0.0.9.data/data/teradatasqlalchemy/README.md
teradatasqlalchemy-20.0.0.9.dist-info/LICENSE-3RD-PARTY.pdf
teradatasqlalchemy-20.0.0.9.dist-info/LICENSE.pdf
teradatasqlalchemy-20.0.0.9.dist-info/METADATA
teradatasqlalchemy-20.0.0.9.dist-info/WHEEL
teradatasqlalchemy-20.0.0.9.dist-info/entry_points.txt
teradatasqlalchemy-20.0.0.9.dist-info/top_level.txt
teradatasqlalchemy-20.0.0.9.dist-info/RECORD
