Metadata-Version: 2.1
Name: teradatasqlalchemy
Version: 20.0.0.9
Summary: Teradata SQL Driver Dialect for SQLAlchemy
Home-page: http://www.teradata.com/
Author: Teradata Corporation
Author-email: teradatasql@teradata.com
License: Teradata License Agreement
Keywords: Teradata
Platform: Windows
Platform: MacOS X
Platform: Linux
Classifier: Programming Language :: Python :: 3 :: Only
Classifier: Programming Language :: Python :: 3.4
Classifier: Programming Language :: Python :: 3.5
Classifier: Programming Language :: Python :: 3.6
Classifier: Programming Language :: Python :: 3.7
Classifier: Operating System :: Microsoft :: Windows
Classifier: Operating System :: MacOS :: MacOS X
Classifier: Operating System :: POSIX :: Linux
Classifier: Topic :: Database :: Front-Ends
Classifier: License :: Other/Proprietary License
Requires-Python: >=3.4
Requires-Dist: sqlalchemy (>=1.4.0)
Requires-Dist: teradatasql (>=17.0.0.2)
